rdflib_ocdm/__init__.py
rdflib_ocdm/abstract_entity.py
rdflib_ocdm/counter_handler/__init__.py
rdflib_ocdm/counter_handler/counter_handler.py
rdflib_ocdm/counter_handler/filesystem_counter_handler.py
rdflib_ocdm/counter_handler/in_memory_counter_handler.py
rdflib_ocdm/counter_handler/redis_counter_handler.py
rdflib_ocdm/counter_handler/sqlite_counter_handler.py
rdflib_ocdm/ocdm_graph.py
rdflib_ocdm/prov/__init__.py
rdflib_ocdm/prov/prov_entity.py
rdflib_ocdm/prov/provenance.py
rdflib_ocdm/prov/snapshot_entity.py
rdflib_ocdm/query_utils.py
rdflib_ocdm/reader.py
rdflib_ocdm/retry_utils.py
rdflib_ocdm/storer.py
rdflib_ocdm/support.py
rdflib_ocdm-1.0.4.dist-info/LICENSE
rdflib_ocdm-1.0.4.dist-info/METADATA
rdflib_ocdm-1.0.4.dist-info/WHEEL
rdflib_ocdm-1.0.4.dist-info/RECORD
