Metadata-Version: 2.3
Name: rdflib-ocdm
Version: 1.0.4
Summary: 
License: ISC
Author: arcangelo7
Author-email: arcangelomas@gmail.com
Requires-Python: >=3.9,<3.14
Classifier: License :: OSI Approved
Classifier: Programming Language :: Python :: 3
Classifier: Programming Language :: Python :: 3.9
Classifier: Programming Language :: Python :: 3.10
Classifier: Programming Language :: Python :: 3.11
Classifier: Programming Language :: Python :: 3.12
Classifier: Programming Language :: Python :: 3.13
Requires-Dist: oc-ocdm (>=9.2.2,<10.0.0)
Requires-Dist: rdflib (>=7.1.4,<8.0.0)
Requires-Dist: redis (>=4.5.5,<5.0.0)
Requires-Dist: sparqlwrapper (>=2.0.0,<3.0.0)
